odoo/addons/ssi_backend_mixin/README.rst
odoo/addons/ssi_backend_mixin/__init__.py
odoo/addons/ssi_backend_mixin/__manifest__.py
odoo/addons/ssi_backend_mixin/i18n/ssi_backend_mixin.pot
odoo/addons/ssi_backend_mixin/models/__init__.py
odoo/addons/ssi_backend_mixin/models/backend_mixin.py
odoo/addons/ssi_backend_mixin/static/description/icon.png
odoo/addons/ssi_backend_mixin/views/mixin_backend_views.xml
odoo/addons/ssi_backend_mixin/views/res_company_views.xml
odoo14_addon_ssi_backend_mixin-14.0.1.0.1.dev1.dist-info/METADATA
odoo14_addon_ssi_backend_mixin-14.0.1.0.1.dev1.dist-info/WHEEL
odoo14_addon_ssi_backend_mixin-14.0.1.0.1.dev1.dist-info/top_level.txt
odoo14_addon_ssi_backend_mixin-14.0.1.0.1.dev1.dist-info/RECORD
